{"blocks":[{"type":"inline","id":"d80bb9595a69","properties":[],"hasRule":true,"nested":[{"type":"group","id":"9bfa39b90a99","properties":["name","description","aspects","temporaryAspects"],"nested":[{"type":"heading","id":"f86a8a894bb9","properties":["name"],"conditioned":true,"size":1},{"type":"text","id":"88fb189a5bc9","properties":["description"],"conditioned":true,"markdown":true,"text":null,"dice":false},{"type":"text","id":"99998be93b3a","properties":["aspects"],"markdown":true,"text":null,"dice":false,"conditioned":true,"heading":"Aspects"},{"type":"text","id":"39885989eb69","properties":["temporaryAspects"],"markdown":true,"text":null,"dice":false,"conditioned":true,"heading":"Temporary Aspects"}],"conditioned":true},{"type":"image","id":"19c9ab0998a9","properties":["image"],"conditioned":true}]},{"type":"table","id":"c80b981ab868","properties":["stress"],"headers":["Physical","Mental"],"calculate":false,"hasRule":true,"conditioned":true},{"type":"traits","id":"6ba97abb49e8","properties":["consequences"],"conditioned":true,"heading":"Consequences"},{"type":"traits","id":"19d8e849790a","properties":["skills"],"conditioned":true,"hasRule":false,"heading":"Skills"},{"type":"traits","id":"cb6b781a4a6b","properties":["stunts"],"markdown":true,"dice":false,"conditioned":true,"heading":"Stunts"},{"type":"traits","id":"f9a9a9ba08fb","properties":["items"],"heading":"Items","conditioned":true,"markdown":true,"dice":false},{"type":"traits","id":"c9fb2bdacbb8","properties":["extras"],"heading":"Extras","conditioned":true,"markdown":true,"dice":false}],"id":"basic-fate-core-layout","name":"Basic Fate Core Layout","edited":false}